{"otherData": {},"traceEvents":[{"cat":"function","dur":0,"name":"void __cdecl Mayhem::Renderer2D::shutdown(void)","ph":"X","pid":0,"tid":1364537591,"ts":230216873969},{"cat":"function","dur":73,"name":"__cdecl Mayhem::Application::~Application(void)","ph":"X","pid":0,"tid":1364537591,"ts":230216873968},{"cat":"function","dur":2,"name":"__cdecl Mayhem::OpenGLTexture2D::~OpenGLTexture2D(void)","ph":"X","pid":0,"tid":1364537591,"ts":230216874104},{"cat":"function","dur":15346,"name":"void __cdecl Mayhem::WindowsWindow::shutdown(void)","ph":"X","pid":0,"tid":1364537591,"ts":230216874174},{"cat":"function","dur":15477,"name":"__cdecl Mayhem::WindowsWindow::~WindowsWindow(void)","ph":"X","pid":0,"tid":1364537591,"ts":230216874173}]}